{
  "assets" : {
    "26B3968023D974BC92E987BB6D66F9F7" : {
      "type" : "texture",
      "index" : 5,
      "assetRequest" : {
        "type" : "slide",
        "state" : "contents",
        "slide" : "none"
      },
      "url" : {
        "native" : "assets\/94991B94-8921-4A9E-9461-598603CA1924.pdf"
      },
      "width" : 907,
      "height" : 98
    },
    "F6DEC8FEAF1136F82C92EECECA5A5528" : {
      "type" : "texture",
      "index" : 2,
      "assetRequest" : {
        "type" : "slide",
        "state" : "contents",
        "slide" : "none"
      },
      "url" : {
        "native" : "assets\/94991B94-8921-4A9E-9461-598603CA1924.pdf"
      },
      "width" : 202,
      "height" : 46
    },
    "1978888DB9C355C7FA645F786AA444ED" : {
      "type" : "texture",
      "index" : 3,
      "assetRequest" : {
        "type" : "slide",
        "state" : "contents",
        "slide" : "none"
      },
      "url" : {
        "native" : "assets\/94991B94-8921-4A9E-9461-598603CA1924.pdf"
      },
      "width" : 806,
      "height" : 340
    },
    "9D0AE086D0C1FE5F9359FFEC9773AD39" : {
      "type" : "texture",
      "index" : 6,
      "assetRequest" : {
        "type" : "slide",
        "state" : "contents",
        "slide" : "none"
      },
      "url" : {
        "native" : "assets\/94991B94-8921-4A9E-9461-598603CA1924.pdf"
      },
      "width" : 1024,
      "height" : 768
    },
    "DC6B483739B2B3911BF1A32C018C6BFA" : {
      "type" : "texture",
      "index" : 4,
      "assetRequest" : {
        "type" : "slide",
        "state" : "contents",
        "slide" : "none"
      },
      "url" : {
        "native" : "assets\/94991B94-8921-4A9E-9461-598603CA1924.pdf"
      },
      "width" : 924,
      "height" : 98
    },
    "E2B2952C5DCEE4859C285924416B1FDA" : {
      "type" : "texture",
      "index" : 7,
      "assetRequest" : {
        "type" : "slide",
        "state" : "contents",
        "slide" : "none"
      },
      "url" : {
        "native" : "assets\/94991B94-8921-4A9E-9461-598603CA1924.pdf"
      },
      "width" : 1024,
      "height" : 768
    },
    "2D39D5FEB91729918C19454A1768D07B" : {
      "type" : "texture",
      "index" : 1,
      "assetRequest" : {
        "type" : "slide",
        "state" : "contents",
        "slide" : "none"
      },
      "url" : {
        "native" : "assets\/94991B94-8921-4A9E-9461-598603CA1924.pdf"
      },
      "width" : 942,
      "height" : 8
    },
    "498E23C82CA78A4BCD7BA88E5243B6FC" : {
      "type" : "texture",
      "index" : 0,
      "assetRequest" : {
        "type" : "slide",
        "state" : "contents",
        "slide" : "none"
      },
      "url" : {
        "native" : "assets\/94991B94-8921-4A9E-9461-598603CA1924.pdf"
      },
      "width" : 1024,
      "height" : 768
    }
  },
  "events" : [
    {
      "effects" : [
        {
          "beginTime" : 0,
          "baseLayer" : {
            "animations" : [

            ],
            "initialState" : {
              "affineTransform" : [
                1,
                0,
                0,
                1,
                0,
                0
              ],
              "masksToBounds" : false,
              "rotation" : 0,
              "scale" : 1,
              "position" : {
                "pointX" : 512,
                "pointY" : 384
              },
              "width" : 1024,
              "sublayerTransform" : [
                1,
                0,
                0,
                0,
                0,
                1,
                0,
                0,
                0,
                0,
                1,
                0,
                0,
                0,
                0,
                1
              ],
              "contentsRect" : {
                "y" : 0,
                "x" : 0,
                "width" : 1,
                "height" : 1
              },
              "opacity" : 1,
              "edgeAntialiasingMask" : 251658240,
              "height" : 768,
              "hidden" : false,
              "anchorPoint" : {
                "pointX" : 0.5,
                "pointY" : 0.5
              }
            },
            "objectID" : "0",
            "layers" : [
              {
                "animations" : [

                ],
                "initialState" : {
                  "affineTransform" : [
                    1,
                    0,
                    0,
                    1,
                    0,
                    0
                  ],
                  "masksToBounds" : false,
                  "rotation" : 0,
                  "scale" : 1,
                  "position" : {
                    "pointX" : 512,
                    "pointY" : 384
                  },
                  "width" : 1024,
                  "sublayerTransform" : [
                    1,
                    0,
                    0,
                    0,
                    0,
                    1,
                    0,
                    0,
                    0,
                    0,
                    1,
                    -0.00049229876906403734,
                    0,
                    0,
                    0,
                    1
                  ],
                  "contentsRect" : {
                    "y" : 0,
                    "x" : 0,
                    "width" : 1,
                    "height" : 1
                  },
                  "opacity" : 1,
                  "edgeAntialiasingMask" : 251658240,
                  "height" : 768,
                  "hidden" : false,
                  "anchorPoint" : {
                    "pointX" : 0.5,
                    "pointY" : 0.5
                  }
                },
                "layers" : [
                  {
                    "animations" : [

                    ],
                    "layers" : [

                    ],
                    "texturedRectangle" : {
                      "isBackgroundTexture" : false,
                      "singleTextureOpacity" : 1,
                      "textureType" : 0,
                      "textBaseline" : 0,
                      "textXHeight" : 0,
                      "isVerticalText" : false
                    },
                    "initialState" : {
                      "affineTransform" : [
                        1,
                        0,
                        0,
                        1,
                        0,
                        0
                      ],
                      "masksToBounds" : false,
                      "rotation" : 0,
                      "scale" : 1,
                      "position" : {
                        "pointX" : 512,
                        "pointY" : 384
                      },
                      "width" : 1024,
                      "sublayerTransform" : [
                        1,
                        0,
                        0,
                        0,
                        0,
                        1,
                        0,
                        0,
                        0,
                        0,
                        1,
                        0,
                        0,
                        0,
                        0,
                        1
                      ],
                      "contentsRect" : {
                        "y" : 0,
                        "x" : 0,
                        "width" : 1,
                        "height" : 1
                      },
                      "opacity" : 1,
                      "edgeAntialiasingMask" : 0,
                      "height" : 768,
                      "hidden" : false,
                      "anchorPoint" : {
                        "pointX" : 0.5,
                        "pointY" : 0.5
                      }
                    },
                    "texture" : "9D0AE086D0C1FE5F9359FFEC9773AD39"
                  },
                  {
                    "animations" : [
                      {
                        "timeOffset" : 0,
                        "from" : {
                          "scalar" : false
                        },
                        "beginTime" : 0,
                        "repeatCount" : 0,
                        "fillMode" : "both",
                        "property" : "hidden",
                        "autoreverses" : false,
                        "duration" : 0.01,
                        "to" : {
                          "scalar" : true
                        }
                      }
                    ],
                    "layers" : [

                    ],
                    "texturedRectangle" : {
                      "isBackgroundTexture" : false,
                      "singleTextureOpacity" : 1,
                      "textureType" : 0,
                      "textBaseline" : 0,
                      "textXHeight" : 0,
                      "isVerticalText" : false
                    },
                    "initialState" : {
                      "affineTransform" : [
                        1,
                        0,
                        0,
                        1,
                        0,
                        0
                      ],
                      "masksToBounds" : false,
                      "rotation" : 0,
                      "scale" : 1,
                      "position" : {
                        "pointX" : 512,
                        "pointY" : 384
                      },
                      "width" : 1024,
                      "sublayerTransform" : [
                        1,
                        0,
                        0,
                        0,
                        0,
                        1,
                        0,
                        0,
                        0,
                        0,
                        1,
                        0,
                        0,
                        0,
                        0,
                        1
                      ],
                      "contentsRect" : {
                        "y" : 0,
                        "x" : 0,
                        "width" : 1,
                        "height" : 1
                      },
                      "opacity" : 1,
                      "edgeAntialiasingMask" : 0,
                      "height" : 768,
                      "hidden" : false,
                      "anchorPoint" : {
                        "pointX" : 0.5,
                        "pointY" : 0.5
                      }
                    },
                    "texture" : "E2B2952C5DCEE4859C285924416B1FDA"
                  }
                ]
              }
            ]
          },
          "effects" : [

          ],
          "duration" : 0.01,
          "type" : "transition",
          "name" : "none",
          "objectID" : "0"
        }
      ],
      "automaticPlay" : false,
      "hyperlinks" : [
        {
          "url" : "http:\/\/sa.previdencia.gov.br\/site\/2018\/06\/Indicador-de-Situacao-Previdenciaria-ISP-01-2018-Relatorio-2018061....pdf",
          "targetRectangle" : {
            "y" : 168.19996824811372,
            "x" : 43.172403337618277,
            "width" : 922.54531206190586,
            "height" : 95.999999999999972
          }
        },
        {
          "url" : "https:\/\/drive.google.com\/file\/d\/0BzS_UG2IfnTmcXR3T1lIeXlfa1FCcXhieEIzcG1SY2NlZS1J\/view?usp=sharing",
          "targetRectangle" : {
            "y" : 293.16124208590952,
            "x" : 46.878686981913404,
            "width" : 904.48421829938889,
            "height" : 96
          }
        }
      ],
      "accessibility" : [
        {
          "text" : "SECRETARIA DE PREVIDÊNCIA (SPrev), Subsecretaria dos Regimes Próprios de Previdência Social – SRPPS, Indicador de Situação Previdenciária \/ ISP-RPPS-2018- 01.Relatório. Brasil, 2018.",
          "targetRectangle" : {
            "y" : 168.19996824811372,
            "x" : 43.172403337618277,
            "width" : 922.54531206190586,
            "height" : 95.999999999999972
          }
        },
        {
          "text" : "REFERÊNCIAS",
          "targetRectangle" : {
            "y" : 61,
            "x" : 49,
            "width" : 203.11200000000005,
            "height" : 48.328147583007819
          }
        },
        {
          "text" : "Captura de Tela 2019-07-05 às 11.08.28.png",
          "targetRectangle" : {
            "y" : 414.12251603158433,
            "x" : 110.76034556260811,
            "width" : 802.47930908203125,
            "height" : 337.36071777343756
          }
        },
        {
          "text" : "THAÍNA S. V. CHAVARRY, Indicador de Situação Previdenciária dos Regimes Próprios e seu Desempenho nos Entes Subnacionais Brasileiros \/ UnB, Brasília, Brasil, 2019.",
          "targetRectangle" : {
            "y" : 293.16124208590952,
            "x" : 46.878686981913404,
            "width" : 904.48421829938889,
            "height" : 96
          }
        }
      ],
      "baseLayer" : {
        "animations" : [

        ],
        "initialState" : {
          "affineTransform" : [
            1,
            0,
            0,
            1,
            0,
            0
          ],
          "masksToBounds" : false,
          "rotation" : 0,
          "scale" : 1,
          "position" : {
            "pointX" : 512,
            "pointY" : 384
          },
          "width" : 1024,
          "sublayerTransform" : [
            1,
            0,
            0,
            0,
            0,
            1,
            0,
            0,
            0,
            0,
            1,
            0,
            0,
            0,
            0,
            1
          ],
          "contentsRect" : {
            "y" : 0,
            "x" : 0,
            "width" : 1,
            "height" : 1
          },
          "opacity" : 1,
          "edgeAntialiasingMask" : 251658240,
          "height" : 768,
          "hidden" : false,
          "anchorPoint" : {
            "pointX" : 0.5,
            "pointY" : 0.5
          }
        },
        "objectID" : "0",
        "layers" : [
          {
            "animations" : [

            ],
            "initialState" : {
              "affineTransform" : [
                1,
                0,
                0,
                1,
                0,
                0
              ],
              "masksToBounds" : false,
              "rotation" : 0,
              "scale" : 1,
              "position" : {
                "pointX" : 512,
                "pointY" : 384
              },
              "width" : 1024,
              "sublayerTransform" : [
                1,
                0,
                0,
                0,
                0,
                1,
                0,
                0,
                0,
                0,
                1,
                0,
                0,
                0,
                0,
                1
              ],
              "contentsRect" : {
                "y" : 0,
                "x" : 0,
                "width" : 1,
                "height" : 1
              },
              "opacity" : 1,
              "edgeAntialiasingMask" : 251658240,
              "height" : 768,
              "hidden" : false,
              "anchorPoint" : {
                "pointX" : 0.5,
                "pointY" : 0.5
              }
            },
            "layers" : [
              {
                "animations" : [

                ],
                "initialState" : {
                  "affineTransform" : [
                    1,
                    0,
                    0,
                    1,
                    0,
                    0
                  ],
                  "masksToBounds" : false,
                  "rotation" : 0,
                  "scale" : 1,
                  "position" : {
                    "pointX" : 512,
                    "pointY" : 384
                  },
                  "width" : 1024,
                  "sublayerTransform" : [
                    1,
                    0,
                    0,
                    0,
                    0,
                    1,
                    0,
                    0,
                    0,
                    0,
                    1,
                    0,
                    0,
                    0,
                    0,
                    1
                  ],
                  "contentsRect" : {
                    "y" : 0,
                    "x" : 0,
                    "width" : 1,
                    "height" : 1
                  },
                  "opacity" : 1,
                  "edgeAntialiasingMask" : 251658240,
                  "height" : 768,
                  "hidden" : false,
                  "anchorPoint" : {
                    "pointX" : 0.5,
                    "pointY" : 0.5
                  }
                },
                "layers" : [
                  {
                    "animations" : [

                    ],
                    "layers" : [

                    ],
                    "texturedRectangle" : {
                      "isBackgroundTexture" : true,
                      "singleTextureOpacity" : 1,
                      "textureType" : 1,
                      "textBaseline" : 0,
                      "textXHeight" : 0,
                      "isVerticalText" : false
                    },
                    "initialState" : {
                      "affineTransform" : [
                        1,
                        0,
                        0,
                        1,
                        0,
                        0
                      ],
                      "masksToBounds" : false,
                      "rotation" : 0,
                      "scale" : 1,
                      "position" : {
                        "pointX" : 512,
                        "pointY" : 384
                      },
                      "width" : 1024,
                      "sublayerTransform" : [
                        1,
                        0,
                        0,
                        0,
                        0,
                        1,
                        0,
                        0,
                        0,
                        0,
                        1,
                        0,
                        0,
                        0,
                        0,
                        1
                      ],
                      "contentsRect" : {
                        "y" : 0,
                        "x" : 0,
                        "width" : 1,
                        "height" : 1
                      },
                      "opacity" : 1,
                      "edgeAntialiasingMask" : 0,
                      "height" : 768,
                      "hidden" : false,
                      "anchorPoint" : {
                        "pointX" : 0.5,
                        "pointY" : 0.5
                      }
                    },
                    "texture" : "498E23C82CA78A4BCD7BA88E5243B6FC"
                  }
                ]
              }
            ]
          },
          {
            "animations" : [

            ],
            "initialState" : {
              "affineTransform" : [
                1,
                0,
                0,
                1,
                0,
                0
              ],
              "masksToBounds" : false,
              "rotation" : 0,
              "scale" : 1,
              "position" : {
                "pointX" : 512,
                "pointY" : 384
              },
              "width" : 1024,
              "sublayerTransform" : [
                1,
                0,
                0,
                0,
                0,
                1,
                0,
                0,
                0,
                0,
                1,
                0,
                0,
                0,
                0,
                1
              ],
              "contentsRect" : {
                "y" : 0,
                "x" : 0,
                "width" : 1,
                "height" : 1
              },
              "opacity" : 1,
              "edgeAntialiasingMask" : 251658240,
              "height" : 768,
              "hidden" : false,
              "anchorPoint" : {
                "pointX" : 0.5,
                "pointY" : 0.5
              }
            },
            "layers" : [
              {
                "animations" : [

                ],
                "initialState" : {
                  "affineTransform" : [
                    1,
                    0,
                    0,
                    1,
                    0,
                    0
                  ],
                  "masksToBounds" : false,
                  "rotation" : 0,
                  "scale" : 1,
                  "position" : {
                    "pointX" : 513.87867965644034,
                    "pointY" : 125.87867965644035
                  },
                  "width" : 942,
                  "sublayerTransform" : [
                    1,
                    0,
                    0,
                    0,
                    0,
                    1,
                    0,
                    0,
                    0,
                    0,
                    1,
                    0,
                    0,
                    0,
                    0,
                    1
                  ],
                  "contentsRect" : {
                    "y" : 0,
                    "x" : 0,
                    "width" : 1,
                    "height" : 1
                  },
                  "opacity" : 1,
                  "edgeAntialiasingMask" : 251658240,
                  "height" : 8,
                  "hidden" : false,
                  "anchorPoint" : {
                    "pointX" : 0.5,
                    "pointY" : 0.5
                  }
                },
                "layers" : [
                  {
                    "animations" : [

                    ],
                    "layers" : [

                    ],
                    "texturedRectangle" : {
                      "singleTextureOpacity" : 1,
                      "textXHeight" : 0,
                      "shapePath" : {
                        "lineWidth" : 1,
                        "flatness" : 0.59999999999999998,
                        "lineCapStyle" : 0,
                        "elements" : [
                          {
                            "type" : "MoveToPoint",
                            "points" : [
                              [
                                4,
                                4
                              ]
                            ]
                          },
                          {
                            "type" : "AddLine",
                            "points" : [
                              [
                                938,
                                4
                              ]
                            ]
                          }
                        ],
                        "windingRule" : 0,
                        "lineJoinStyle" : 0,
                        "miterLimit" : 10
                      },
                      "isBackgroundTexture" : true,
                      "textBaseline" : 0,
                      "isVerticalText" : false,
                      "textureType" : 5
                    },
                    "initialState" : {
                      "affineTransform" : [
                        1,
                        0,
                        0,
                        1,
                        0,
                        0
                      ],
                      "masksToBounds" : false,
                      "rotation" : 0,
                      "scale" : 1,
                      "position" : {
                        "pointX" : 469.12132034355966,
                        "pointY" : 2.1213203435596455
                      },
                      "width" : 942,
                      "sublayerTransform" : [
                        1,
                        0,
                        0,
                        0,
                        0,
                        1,
                        0,
                        0,
                        0,
                        0,
                        1,
                        0,
                        0,
                        0,
                        0,
                        1
                      ],
                      "contentsRect" : {
                        "y" : 0,
                        "x" : 0,
                        "width" : 1,
                        "height" : 1
                      },
                      "opacity" : 1,
                      "edgeAntialiasingMask" : 0,
                      "height" : 8,
                      "hidden" : false,
                      "anchorPoint" : {
                        "pointX" : 0.5,
                        "pointY" : 0.5
                      }
                    },
                    "texture" : "2D39D5FEB91729918C19454A1768D07B"
                  }
                ]
              }
            ]
          },
          {
            "animations" : [

            ],
            "initialState" : {
              "affineTransform" : [
                1,
                0,
                0,
                1,
                0,
                0
              ],
              "masksToBounds" : false,
              "rotation" : 0,
              "scale" : 1,
              "position" : {
                "pointX" : 512,
                "pointY" : 384
              },
              "width" : 1024,
              "sublayerTransform" : [
                1,
                0,
                0,
                0,
                0,
                1,
                0,
                0,
                0,
                0,
                1,
                0,
                0,
                0,
                0,
                1
              ],
              "contentsRect" : {
                "y" : 0,
                "x" : 0,
                "width" : 1,
                "height" : 1
              },
              "opacity" : 1,
              "edgeAntialiasingMask" : 251658240,
              "height" : 768,
              "hidden" : false,
              "anchorPoint" : {
                "pointX" : 0.5,
                "pointY" : 0.5
              }
            },
            "layers" : [
              {
                "animations" : [

                ],
                "initialState" : {
                  "affineTransform" : [
                    1,
                    0,
                    0,
                    1,
                    0,
                    0
                  ],
                  "masksToBounds" : false,
                  "rotation" : 0,
                  "scale" : 1,
                  "position" : {
                    "pointX" : 146,
                    "pointY" : 80
                  },
                  "width" : 202,
                  "sublayerTransform" : [
                    1,
                    0,
                    0,
                    0,
                    0,
                    1,
                    0,
                    0,
                    0,
                    0,
                    1,
                    0,
                    0,
                    0,
                    0,
                    1
                  ],
                  "contentsRect" : {
                    "y" : 0,
                    "x" : 0,
                    "width" : 1,
                    "height" : 1
                  },
                  "opacity" : 1,
                  "edgeAntialiasingMask" : 251658240,
                  "height" : 46,
                  "hidden" : false,
                  "anchorPoint" : {
                    "pointX" : 0.5,
                    "pointY" : 0.5
                  }
                },
                "layers" : [
                  {
                    "animations" : [

                    ],
                    "layers" : [

                    ],
                    "texturedRectangle" : {
                      "singleTextureOpacity" : 1,
                      "textXHeight" : 0.53301130434782606,
                      "textBaseline" : 0.96523345947265615,
                      "isBackgroundTexture" : true,
                      "isVerticalText" : false,
                      "textColor" : [
                        0,
                        0,
                        0,
                        1
                      ],
                      "textureType" : 6
                    },
                    "initialState" : {
                      "affineTransform" : [
                        1,
                        0,
                        0,
                        1,
                        0,
                        0
                      ],
                      "masksToBounds" : false,
                      "rotation" : 0,
                      "scale" : 1,
                      "position" : {
                        "pointX" : 106,
                        "pointY" : 17
                      },
                      "width" : 202,
                      "sublayerTransform" : [
                        1,
                        0,
                        0,
                        0,
                        0,
                        1,
                        0,
                        0,
                        0,
                        0,
                        1,
                        0,
                        0,
                        0,
                        0,
                        1
                      ],
                      "contentsRect" : {
                        "y" : 0,
                        "x" : 0,
                        "width" : 1,
                        "height" : 1
                      },
                      "opacity" : 1,
                      "edgeAntialiasingMask" : 0,
                      "height" : 46,
                      "hidden" : false,
                      "anchorPoint" : {
                        "pointX" : 0.5,
                        "pointY" : 0.5
                      }
                    },
                    "texture" : "F6DEC8FEAF1136F82C92EECECA5A5528"
                  }
                ]
              }
            ]
          },
          {
            "animations" : [

            ],
            "initialState" : {
              "affineTransform" : [
                1,
                0,
                0,
                1,
                0,
                0
              ],
              "masksToBounds" : false,
              "rotation" : 0,
              "scale" : 1,
              "position" : {
                "pointX" : 512,
                "pointY" : 384
              },
              "width" : 1024,
              "sublayerTransform" : [
                1,
                0,
                0,
                0,
                0,
                1,
                0,
                0,
                0,
                0,
                1,
                0,
                0,
                0,
                0,
                1
              ],
              "contentsRect" : {
                "y" : 0,
                "x" : 0,
                "width" : 1,
                "height" : 1
              },
              "opacity" : 1,
              "edgeAntialiasingMask" : 251658240,
              "height" : 768,
              "hidden" : false,
              "anchorPoint" : {
                "pointX" : 0.5,
                "pointY" : 0.5
              }
            },
            "layers" : [
              {
                "animations" : [

                ],
                "initialState" : {
                  "affineTransform" : [
                    1,
                    0,
                    0,
                    1,
                    0,
                    0
                  ],
                  "masksToBounds" : false,
                  "rotation" : 0,
                  "scale" : 1,
                  "position" : {
                    "pointX" : 513.76034556260811,
                    "pointY" : 584.12251603158438
                  },
                  "width" : 806,
                  "sublayerTransform" : [
                    1,
                    0,
                    0,
                    0,
                    0,
                    1,
                    0,
                    0,
                    0,
                    0,
                    1,
                    0,
                    0,
                    0,
                    0,
                    1
                  ],
                  "contentsRect" : {
                    "y" : 0,
                    "x" : 0,
                    "width" : 1,
                    "height" : 1
                  },
                  "opacity" : 1,
                  "edgeAntialiasingMask" : 251658240,
                  "height" : 340,
                  "hidden" : false,
                  "anchorPoint" : {
                    "pointX" : 0.5,
                    "pointY" : 0.5
                  }
                },
                "layers" : [
                  {
                    "animations" : [

                    ],
                    "layers" : [

                    ],
                    "texturedRectangle" : {
                      "isBackgroundTexture" : true,
                      "singleTextureOpacity" : 1,
                      "textureType" : 5,
                      "textBaseline" : 0,
                      "textXHeight" : 0,
                      "isVerticalText" : false
                    },
                    "initialState" : {
                      "affineTransform" : [
                        1,
                        0,
                        0,
                        1,
                        0,
                        0
                      ],
                      "masksToBounds" : false,
                      "rotation" : 0,
                      "scale" : 1,
                      "position" : {
                        "pointX" : 401.23965443739189,
                        "pointY" : 168.87748396841567
                      },
                      "width" : 806,
                      "sublayerTransform" : [
                        1,
                        0,
                        0,
                        0,
                        0,
                        1,
                        0,
                        0,
                        0,
                        0,
                        1,
                        0,
                        0,
                        0,
                        0,
                        1
                      ],
                      "contentsRect" : {
                        "y" : 0,
                        "x" : 0,
                        "width" : 1,
                        "height" : 1
                      },
                      "opacity" : 1,
                      "edgeAntialiasingMask" : 0,
                      "height" : 340,
                      "hidden" : false,
                      "anchorPoint" : {
                        "pointX" : 0.5,
                        "pointY" : 0.5
                      }
                    },
                    "texture" : "1978888DB9C355C7FA645F786AA444ED"
                  }
                ]
              }
            ]
          },
          {
            "animations" : [

            ],
            "initialState" : {
              "affineTransform" : [
                1,
                0,
                0,
                1,
                0,
                0
              ],
              "masksToBounds" : false,
              "rotation" : 0,
              "scale" : 1,
              "position" : {
                "pointX" : 512,
                "pointY" : 384
              },
              "width" : 1024,
              "sublayerTransform" : [
                1,
                0,
                0,
                0,
                0,
                1,
                0,
                0,
                0,
                0,
                1,
                0,
                0,
                0,
                0,
                1
              ],
              "contentsRect" : {
                "y" : 0,
                "x" : 0,
                "width" : 1,
                "height" : 1
              },
              "opacity" : 1,
              "edgeAntialiasingMask" : 251658240,
              "height" : 768,
              "hidden" : false,
              "anchorPoint" : {
                "pointX" : 0.5,
                "pointY" : 0.5
              }
            },
            "layers" : [
              {
                "animations" : [

                ],
                "initialState" : {
                  "affineTransform" : [
                    1,
                    0,
                    0,
                    1,
                    0,
                    0
                  ],
                  "masksToBounds" : false,
                  "rotation" : 0,
                  "scale" : 1,
                  "position" : {
                    "pointX" : 501.17240333761828,
                    "pointY" : 213.19996824811372
                  },
                  "width" : 924,
                  "sublayerTransform" : [
                    1,
                    0,
                    0,
                    0,
                    0,
                    1,
                    0,
                    0,
                    0,
                    0,
                    1,
                    0,
                    0,
                    0,
                    0,
                    1
                  ],
                  "contentsRect" : {
                    "y" : 0,
                    "x" : 0,
                    "width" : 1,
                    "height" : 1
                  },
                  "opacity" : 1,
                  "edgeAntialiasingMask" : 251658240,
                  "height" : 98,
                  "hidden" : false,
                  "anchorPoint" : {
                    "pointX" : 0.5,
                    "pointY" : 0.5
                  }
                },
                "layers" : [
                  {
                    "animations" : [

                    ],
                    "layers" : [

                    ],
                    "texturedRectangle" : {
                      "singleTextureOpacity" : 1,
                      "textXHeight" : 0.205078125,
                      "textBaseline" : 0.92724377676646652,
                      "isBackgroundTexture" : true,
                      "isVerticalText" : false,
                      "textColor" : [
                        0.36176085472106934,
                        0.3617607057094574,
                        0.36176073551177979,
                        1
                      ],
                      "textureType" : 6
                    },
                    "initialState" : {
                      "affineTransform" : [
                        1,
                        0,
                        0,
                        1,
                        0,
                        0
                      ],
                      "masksToBounds" : false,
                      "rotation" : 0,
                      "scale" : 1,
                      "position" : {
                        "pointX" : 464.82759666238172,
                        "pointY" : 51.80003175188628
                      },
                      "width" : 924,
                      "sublayerTransform" : [
                        1,
                        0,
                        0,
                        0,
                        0,
                        1,
                        0,
                        0,
                        0,
                        0,
                        1,
                        0,
                        0,
                        0,
                        0,
                        1
                      ],
                      "contentsRect" : {
                        "y" : 0,
                        "x" : 0,
                        "width" : 1,
                        "height" : 1
                      },
                      "opacity" : 1,
                      "edgeAntialiasingMask" : 0,
                      "height" : 98,
                      "hidden" : false,
                      "anchorPoint" : {
                        "pointX" : 0.5,
                        "pointY" : 0.5
                      }
                    },
                    "texture" : "DC6B483739B2B3911BF1A32C018C6BFA"
                  }
                ]
              }
            ]
          },
          {
            "animations" : [

            ],
            "initialState" : {
              "affineTransform" : [
                1,
                0,
                0,
                1,
                0,
                0
              ],
              "masksToBounds" : false,
              "rotation" : 0,
              "scale" : 1,
              "position" : {
                "pointX" : 512,
                "pointY" : 384
              },
              "width" : 1024,
              "sublayerTransform" : [
                1,
                0,
                0,
                0,
                0,
                1,
                0,
                0,
                0,
                0,
                1,
                0,
                0,
                0,
                0,
                1
              ],
              "contentsRect" : {
                "y" : 0,
                "x" : 0,
                "width" : 1,
                "height" : 1
              },
              "opacity" : 1,
              "edgeAntialiasingMask" : 251658240,
              "height" : 768,
              "hidden" : false,
              "anchorPoint" : {
                "pointX" : 0.5,
                "pointY" : 0.5
              }
            },
            "layers" : [
              {
                "animations" : [

                ],
                "initialState" : {
                  "affineTransform" : [
                    1,
                    0,
                    0,
                    1,
                    0,
                    0
                  ],
                  "masksToBounds" : false,
                  "rotation" : 0,
                  "scale" : 1,
                  "position" : {
                    "pointX" : 496.3786869819134,
                    "pointY" : 338.16124208590952
                  },
                  "width" : 907,
                  "sublayerTransform" : [
                    1,
                    0,
                    0,
                    0,
                    0,
                    1,
                    0,
                    0,
                    0,
                    0,
                    1,
                    0,
                    0,
                    0,
                    0,
                    1
                  ],
                  "contentsRect" : {
                    "y" : 0,
                    "x" : 0,
                    "width" : 1,
                    "height" : 1
                  },
                  "opacity" : 1,
                  "edgeAntialiasingMask" : 251658240,
                  "height" : 98,
                  "hidden" : false,
                  "anchorPoint" : {
                    "pointX" : 0.5,
                    "pointY" : 0.5
                  }
                },
                "layers" : [
                  {
                    "animations" : [

                    ],
                    "layers" : [

                    ],
                    "texturedRectangle" : {
                      "singleTextureOpacity" : 1,
                      "textXHeight" : 0.205078125,
                      "textBaseline" : 0.92684861184601552,
                      "isBackgroundTexture" : true,
                      "isVerticalText" : false,
                      "textColor" : [
                        0.36176085472106934,
                        0.3617607057094574,
                        0.36176073551177979,
                        1
                      ],
                      "textureType" : 6
                    },
                    "initialState" : {
                      "affineTransform" : [
                        1,
                        0,
                        0,
                        1,
                        0,
                        0
                      ],
                      "masksToBounds" : false,
                      "rotation" : 0,
                      "scale" : 1,
                      "position" : {
                        "pointX" : 455.6213130180866,
                        "pointY" : 51.838757914090479
                      },
                      "width" : 907,
                      "sublayerTransform" : [
                        1,
                        0,
                        0,
                        0,
                        0,
                        1,
                        0,
                        0,
                        0,
                        0,
                        1,
                        0,
                        0,
                        0,
                        0,
                        1
                      ],
                      "contentsRect" : {
                        "y" : 0,
                        "x" : 0,
                        "width" : 1,
                        "height" : 1
                      },
                      "opacity" : 1,
                      "edgeAntialiasingMask" : 0,
                      "height" : 98,
                      "hidden" : false,
                      "anchorPoint" : {
                        "pointX" : 0.5,
                        "pointY" : 0.5
                      }
                    },
                    "texture" : "26B3968023D974BC92E987BB6D66F9F7"
                  }
                ]
              }
            ]
          }
        ]
      }
    }
  ]
}